nemesis/NEMESIS_pipeline.py
nemesis/__init__.py
nemesis_daxfeliz-0.0.1.dist-info/LICENSE
nemesis_daxfeliz-0.0.1.dist-info/METADATA
nemesis_daxfeliz-0.0.1.dist-info/WHEEL
nemesis_daxfeliz-0.0.1.dist-info/top_level.txt
nemesis_daxfeliz-0.0.1.dist-info/RECORD
