Metadata-Version: 2.1
Name: nemesis-daxfeliz
Version: 0.0.1
Summary: Python modules and scripts used for NEMESIS project.
Home-page: https://github.com/daxfeliz/nemesis
Author: Dax L. Feliz
Author-email: <dax.feliz@vanderbilt.edu>
License: MIT
Keywords: python,astronomy,photometry,TESS
Platform: UNKNOWN
Classifier: Development Status :: 3 - Alpha
Classifier: License :: OSI Approved :: MIT License
Classifier: Intended Audience :: Science/Research
Classifier: Topic :: Scientific/Engineering :: Astronomy
Classifier: Operating System :: OS Independent
Classifier: Programming Language :: Python
Requires-Dist: numpy
Requires-Dist: scipy
Requires-Dist: astropy
Requires-Dist: matplotlib
Requires-Dist: wotan
Requires-Dist: transitleastsquares
Requires-Dist: pandas
Requires-Dist: astroquery
Requires-Dist: fbpca
Provides-Extra: all
Requires-Dist: exoplanet ; extra == 'all'
Requires-Dist: corner ; extra == 'all'
